magyar.py
magyar-4.2.0.dist-info/METADATA
magyar-4.2.0.dist-info/WHEEL
magyar-4.2.0.dist-info/top_level.txt
magyar-4.2.0.dist-info/RECORD
