Metadata-Version: 2.1
Name: magyar
Version: 4.2.0
Summary: Hungarian lists of names,animals,foods, fruits, rivers ,GPS,ZIP, Határon túli magyar települések
Home-page: https://github.com/kobanya/nevek
Author: Nagy Béla
Author-email: nagy.belabudapest@gmail.com
Classifier: Programming Language :: Python :: 3
Classifier: License :: OSI Approved :: MIT License
Classifier: Operating System :: OS Independent
